desuwa/__init__.py
desuwa/cli.py
desuwa/knp_rules/LICENSE.txt
desuwa/knp_rules/README.md
desuwa/knp_rules/bnst_basic.rule
desuwa/knp_rules/mrph_auto_dic.rule
desuwa/knp_rules/mrph_basic.rule
desuwa/knp_rules/mrph_filter.rule
desuwa/knp_rules/mrph_homo.rule
desuwa/predicate.py
desuwa/rule/__init__.py
desuwa/rule/constraint.py
desuwa/rule/mrph.py
desuwa/rule/rule_mrph.py
desuwa/rule/rule_tag.py
desuwa/rule/tag.py
desuwa/rule/template.py
desuwa/rule/util.py
desuwa/util.py
desuwa-1.1.0.dist-info/entry_points.txt
desuwa-1.1.0.dist-info/LICENSE.txt
desuwa-1.1.0.dist-info/WHEEL
desuwa-1.1.0.dist-info/METADATA
desuwa-1.1.0.dist-info/RECORD
