Metadata-Version: 2.1
Name: desuwa
Version: 1.1.0
Summary: Feature annotator based on KNP rule files
Home-page: https://github.com/megagonlabs/desuwa
License: Apache-2.0
Author: Yuta Hayashibe
Author-email: hayashibe@megagon.ai
Maintainer: Yuta Hayashibe
Maintainer-email: hayashibe@megagon.ai
Requires-Python: >=3.7,<4.0
Classifier: License :: OSI Approved :: Apache Software License
Classifier: Programming Language :: Python :: 3
Classifier: Programming Language :: Python :: 3.10
Classifier: Programming Language :: Python :: 3.7
Classifier: Programming Language :: Python :: 3.8
Classifier: Programming Language :: Python :: 3.9
Requires-Dist: dataclasses-json (>=0.5.2,<0.6.0)
Requires-Dist: pyknp (>=0.4.5,<0.5.0)
Requires-Dist: sexpdata (>=0.0.3,<0.0.4)
Project-URL: Repository, https://github.com/megagonlabs/desuwa
